{"__comment":"Designed by Zerahi with BDcraft Cubik PRO 0.95 Beta - http://bdcraft.net","textures":{"particle":"rv:blocks/pureshardblock","texture":"rv:blocks/pureshardblock"},"elements":[{"from":[7.25,-0.5625,6.8125],"to":[8.75,10.4375,9.3125],"shade":false,"faces":{"down":{"uv":[3,9,1,5.5],"texture":"#texture"},"up":{"uv":[13,9.5,15,13],"texture":"#texture"},"north":{"uv":[10,0,12,16],"texture":"#texture"},"south":{"uv":[7,0,9,15.5],"texture":"#texture"},"west":{"uv":[5,0,9,16],"texture":"#texture"},"east":{"uv":[10,0,14,15.5],"texture":"#texture"}}},{"from":[9.72976,0,8],"to":[10.7298,5.5,10],"shade":false,"rotation":{"origin":[9.72976,5.5,8],"axis":"z","angle":-22.5 },"faces":{"down":{"uv":[16,14,14,11],"texture":"#texture"},"up":{"uv":[9,11,11,14],"texture":"#texture"},"north":{"uv":[14,10,16,16],"texture":"#texture"},"south":{"uv":[5,7,7,13],"texture":"#texture"},"west":{"uv":[3,5,6,13],"texture":"#texture"},"east":{"uv":[3,8,6,16],"texture":"#texture"}}},{"from":[5,3,6.875],"to":[6,8.5,8.875],"shade":false,"rotation":{"origin":[5,8.5,6.875],"axis":"z","angle":22.5 },"faces":{"down":{"uv":[4,7,2,4],"texture":"#texture"},"up":{"uv":[2,6,4,9],"texture":"#texture"},"north":{"uv":[7,6,9,16],"texture":"#texture"},"south":{"uv":[5,6,7,16],"texture":"#texture"},"west":{"uv":[4,0,7,10],"texture":"#texture"},"east":{"uv":[3,0,6,10],"texture":"#texture"}}},{"from":[7.5,2.5,5],"to":[8,7.5,6],"shade":false,"rotation":{"origin":[7.5,7.5,5],"axis":"x","angle":-22.5 },"faces":{"down":{"uv":[8,10.5,6.5,8.5],"texture":"#texture"},"up":{"uv":[10,8.5,11.5,10.5],"texture":"#texture"},"north":{"uv":[12,7,13,14],"texture":"#texture"},"south":{"uv":[8,2.5,9,9],"texture":"#texture"},"west":{"uv":[11,5,13,13],"texture":"#texture"},"east":{"uv":[7,1.5,9,9],"texture":"#texture"}}}]}