{
	"__comment": "Designed by Zerahi with Cubik Studio - https://cubik.studio",
	"textures": {
		"particle": "rv:blocks/voidnode",
		"texture": "rv:blocks/voidframe",
		"texture1": "rv:blocks/voidnode"
	},
	"elements": [ 	 
		{
			"__comment": "Box1",
			"from": [ 15, 15, 1 ],
			"to": [ 16, 16, 15 ],
			"faces": {
				"down": { "uv": [ 15, 1, 16, 15 ], "texture": "#texture" },
				"up": { "uv": [ 15, 1, 16, 15 ], "texture": "#texture" },
				"north": { "uv": [ 0, 0, 1, 1 ], "texture": "#texture" },
				"south": { "uv": [ 15, 0, 16, 1 ], "texture": "#texture" },
				"west": { "uv": [ 1, 0, 15, 1 ], "texture": "#texture" },
				"east": { "uv": [ 1, 0, 15, 1 ], "texture": "#texture" }
			}
		},
		{
			"__comment": "Box1",
			"from": [ 0, 1, 15 ],
			"to": [ 1, 15, 16 ],
			"faces": {
				"down": { "uv": [ 0, 0, 1, 1 ], "texture": "#texture" },
				"up": { "uv": [ 0, 15, 1, 16 ], "texture": "#texture" },
				"north": { "uv": [ 15, 1, 16, 15 ], "texture": "#texture" },
				"south": { "uv": [ 0, 1, 1, 15 ], "texture": "#texture" },
				"west": { "uv": [ 15, 1, 16, 15 ], "texture": "#texture" },
				"east": { "uv": [ 0, 1, 1, 15 ], "texture": "#texture" }
			}
		},
		{
			"__comment": "Box1",
			"from": [ 0, 15, 15 ],
			"to": [ 16, 16, 16 ],
			"faces": {
				"down": { "uv": [ 0, 0, 16, 1 ], "texture": "#texture" },
				"up": { "uv": [ 0, 15, 16, 16 ], "texture": "#texture" },
				"north": { "uv": [ 0, 0, 16, 1 ], "texture": "#texture" },
				"south": { "uv": [ 0, 0, 16, 1 ], "texture": "#texture" },
				"west": { "uv": [ 15, 0, 16, 1 ], "texture": "#texture" },
				"east": { "uv": [ 0, 0, 1, 1 ], "texture": "#texture" }
			}
		},
		{
			"__comment": "Box1",
			"from": [ 0, 15, 1 ],
			"to": [ 1, 16, 15 ],
			"faces": {
				"down": { "uv": [ 0, 1, 1, 15 ], "texture": "#texture" },
				"up": { "uv": [ 0, 1, 1, 15 ], "texture": "#texture" },
				"north": { "uv": [ 15, 0, 16, 1 ], "texture": "#texture" },
				"south": { "uv": [ 0, 0, 1, 1 ], "texture": "#texture" },
				"west": { "uv": [ 1, 0, 15, 1 ], "texture": "#texture" },
				"east": { "uv": [ 1, 0, 15, 1 ], "texture": "#texture" }
			}
		},
		{
			"__comment": "Box1",
			"from": [ 15, 0, 1 ],
			"to": [ 16, 1, 15 ],
			"faces": {
				"down": { "uv": [ 15, 1, 16, 15 ], "texture": "#texture" },
				"up": { "uv": [ 15, 1, 16, 15 ], "texture": "#texture" },
				"north": { "uv": [ 0, 15, 1, 16 ], "texture": "#texture" },
				"south": { "uv": [ 15, 15, 16, 16 ], "texture": "#texture" },
				"west": { "uv": [ 1, 15, 15, 16 ], "texture": "#texture" },
				"east": { "uv": [ 1, 15, 15, 16 ], "texture": "#texture" }
			}
		},
		{
			"__comment": "Box1",
			"from": [ 0, 0, 1 ],
			"to": [ 1, 1, 15 ],
			"faces": {
				"down": { "uv": [ 0, 1, 1, 15 ], "texture": "#texture" },
				"up": { "uv": [ 0, 1, 1, 15 ], "texture": "#texture" },
				"north": { "uv": [ 15, 15, 16, 16 ], "texture": "#texture" },
				"south": { "uv": [ 0, 15, 1, 16 ], "texture": "#texture" },
				"west": { "uv": [ 1, 15, 15, 16 ], "texture": "#texture" },
				"east": { "uv": [ 1, 15, 15, 16 ], "texture": "#texture" }
			}
		},
		{
			"__comment": "Box1",
			"from": [ 0, 0, 15 ],
			"to": [ 16, 1, 16 ],
			"faces": {
				"down": { "uv": [ 0, 0, 16, 1 ], "texture": "#texture" },
				"up": { "uv": [ 0, 15, 16, 16 ], "texture": "#texture" },
				"north": { "uv": [ 0, 15, 16, 16 ], "texture": "#texture" },
				"south": { "uv": [ 0, 15, 16, 16 ], "texture": "#texture" },
				"west": { "uv": [ 15, 15, 16, 16 ], "texture": "#texture" },
				"east": { "uv": [ 0, 15, 1, 16 ], "texture": "#texture" }
			}
		},
		{
			"__comment": "Box1",
			"from": [ 0, 0, 0 ],
			"to": [ 16, 1, 1 ],
			"faces": {
				"down": { "uv": [ 0, 15, 16, 16 ], "texture": "#texture" },
				"up": { "uv": [ 0, 0, 16, 1 ], "texture": "#texture" },
				"north": { "uv": [ 0, 15, 16, 16 ], "texture": "#texture" },
				"south": { "uv": [ 0, 15, 16, 16 ], "texture": "#texture" },
				"west": { "uv": [ 0, 15, 1, 16 ], "texture": "#texture" },
				"east": { "uv": [ 15, 15, 16, 16 ], "texture": "#texture" }
			}
		},
		{
			"__comment": "Box1",
			"from": [ 0, 15, 0 ],
			"to": [ 16, 16, 1 ],
			"faces": {
				"down": { "uv": [ 0, 15, 16, 16 ], "texture": "#texture" },
				"up": { "uv": [ 0, 0, 16, 1 ], "texture": "#texture" },
				"north": { "uv": [ 0, 0, 16, 1 ], "texture": "#texture" },
				"south": { "uv": [ 0, 0, 16, 1 ], "texture": "#texture" },
				"west": { "uv": [ 0, 0, 1, 1 ], "texture": "#texture" },
				"east": { "uv": [ 15, 0, 16, 1 ], "texture": "#texture" }
			}
		},
		{
			"__comment": "Box1",
			"from": [ 0, 1, 0 ],
			"to": [ 1, 15, 1 ],
			"faces": {
				"down": { "uv": [ 0, 15, 1, 16 ], "texture": "#texture" },
				"up": { "uv": [ 0, 0, 1, 1 ], "texture": "#texture" },
				"north": { "uv": [ 15, 1, 16, 15 ], "texture": "#texture" },
				"south": { "uv": [ 0, 1, 1, 15 ], "texture": "#texture" },
				"west": { "uv": [ 0, 1, 1, 15 ], "texture": "#texture" },
				"east": { "uv": [ 15, 1, 16, 15 ], "texture": "#texture" }
			}
		},
		{
			"__comment": "Box1",
			"from": [ 15, 1, 0 ],
			"to": [ 16, 15, 1 ],
			"faces": {
				"down": { "uv": [ 15, 15, 16, 16 ], "texture": "#texture" },
				"up": { "uv": [ 15, 0, 16, 1 ], "texture": "#texture" },
				"north": { "uv": [ 0, 1, 1, 15 ], "texture": "#texture" },
				"south": { "uv": [ 15, 1, 16, 15 ], "texture": "#texture" },
				"west": { "uv": [ 0, 1, 1, 15 ], "texture": "#texture" },
				"east": { "uv": [ 15, 1, 16, 15 ], "texture": "#texture" }
			}
		},
		{
			"__comment": "Box1",
			"from": [ 15, 1, 15 ],
			"to": [ 16, 15, 16 ],
			"faces": {
				"down": { "uv": [ 15, 0, 16, 1 ], "texture": "#texture" },
				"up": { "uv": [ 15, 15, 16, 16 ], "texture": "#texture" },
				"north": { "uv": [ 0, 1, 1, 15 ], "texture": "#texture" },
				"south": { "uv": [ 15, 1, 16, 15 ], "texture": "#texture" },
				"west": { "uv": [ 15, 1, 16, 15 ], "texture": "#texture" },
				"east": { "uv": [ 0, 1, 1, 15 ], "texture": "#texture" }
			}
		},
		{
			"__comment": "Box13",
			"from": [ 1, 1, 1 ],
			"to": [ 15, 15, 15 ],
			"faces": {
				"down": { "uv": [ 1, 1, 15, 15 ], "texture": "#texture1" },
				"up": { "uv": [ 1, 1, 15, 15 ], "texture": "#texture1" },
				"north": { "uv": [ 1, 1, 15, 15 ], "texture": "#texture1" },
				"south": { "uv": [ 1, 1, 15, 15 ], "texture": "#texture1" },
				"west": { "uv": [ 1, 1, 15, 15 ], "texture": "#texture1" },
				"east": { "uv": [ 1, 1, 15, 15 ], "texture": "#texture1" }
			}
		}
	]
}